aiogrn/__init__.py
aiogrn/_version.py
aiogrn/client.py
aiogrn-0.0.1.dist-info/DESCRIPTION.rst
aiogrn-0.0.1.dist-info/METADATA
aiogrn-0.0.1.dist-info/metadata.json
aiogrn-0.0.1.dist-info/RECORD
aiogrn-0.0.1.dist-info/top_level.txt
aiogrn-0.0.1.dist-info/WHEEL
