Metadata-Version: 2.0
Name: aiogrn
Version: 0.0.1
Summary: asyncio Groonga Client library
Home-page: https://github.com/hhatto/aiogrn
Author: Hideo Hattori
Author-email: hhatto.jp@gmail.com
License: MIT License
Keywords: asyncio groonga http gqtp
Platform: UNKNOWN
Classifier: Development Status :: 3 - Alpha
Classifier: Programming Language :: Python
Classifier: Programming Language :: Python :: 3
Requires-Dist: aiohttp
Requires-Dist: async-timeout
Requires-Dist: poyonga
